dandi_s3_log_parser/__init__.py
dandi_s3_log_parser/_bin_all_reduced_s3_logs_by_object_key.py
dandi_s3_log_parser/_buffered_text_reader.py
dandi_s3_log_parser/_command_line_interface.py
dandi_s3_log_parser/_config.py
dandi_s3_log_parser/_dandi_s3_log_file_reducer.py
dandi_s3_log_parser/_error_collection.py
dandi_s3_log_parser/_globals.py
dandi_s3_log_parser/_ip_utils.py
dandi_s3_log_parser/_map_binned_s3_logs_to_dandisets.py
dandi_s3_log_parser/_s3_log_file_reducer.py
dandi_s3_log_parser/_s3_log_line_parser.py
dandi_s3_log_parser/testing/__init__.py
dandi_s3_log_parser/testing/_helpers.py
dandi_s3_log_parser-0.4.2.dist-info/METADATA
dandi_s3_log_parser-0.4.2.dist-info/WHEEL
dandi_s3_log_parser-0.4.2.dist-info/entry_points.txt
dandi_s3_log_parser-0.4.2.dist-info/RECORD
