Metadata-Version: 2.3
Name: dandi_s3_log_parser
Version: 0.4.2
Summary: Parse S3 logs to more easily calculate usage metrics per asset.
Author-email: Cody Baker <cody.c.baker.phd@gmail.com>
License: BSD 3-Clause License
Keywords: aws,download tracking,log,s3
Classifier: Intended Audience :: Developers
Classifier: License :: OSI Approved :: BSD License
Classifier: Operating System :: Unix
Classifier: Programming Language :: Python
Classifier: Programming Language :: Python :: 3.12
Requires-Python: >=3.12
Requires-Dist: click
Requires-Dist: dandi
Requires-Dist: ipinfo
Requires-Dist: natsort
Requires-Dist: pandas
Requires-Dist: pyyaml
Requires-Dist: tqdm
